{
  "article_id": "183",
  "comment_index": 21,
  "raw_comment": "Guys this it's really cool to be independent as soon as they turn 18 so they don't talk to their parents as often.",
  "ace_sentences": [
    "Some guys think that it is really cool to be independent as soon as they turn 18.",
    "Some guys think that they do not talk to their parents as often."
  ],
  "source_mappings": {
    "Some guys think that it is really cool to be independent as soon as they turn 18.": [
      "Guys this it's really cool to be independent as soon as they turn 18"
    ],
    "Some guys think that they do not talk to their parents as often.": [
      "they don't talk to their parents as often"
    ]
  }
}